quicksight_bulk_update_datasets.py
quicksight_bulk_update_datasets-0.0.28.dist-info/METADATA
quicksight_bulk_update_datasets-0.0.28.dist-info/WHEEL
quicksight_bulk_update_datasets-0.0.28.dist-info/entry_points.txt
quicksight_bulk_update_datasets-0.0.28.dist-info/licenses/LICENSE
quicksight_bulk_update_datasets-0.0.28.dist-info/RECORD
