Metadata-Version: 2.1
Name: quicksight-bulk-update-datasets
Version: 0.0.28
Summary: CLI to make bulk updates to Quicksight datasets
Project-URL: Source, https://github.com/uktrade/quicksight-bulk-update-datasets
Author-email: Department for Business and Trade <sre@digital.trade.gov.uk>
License-File: LICENSE
Classifier: License :: OSI Approved :: MIT License
Classifier: Programming Language :: Python :: 3
Requires-Python: >=3.6.7
Requires-Dist: boto3>=1.23.10
Requires-Dist: pglast>=6.2
Requires-Dist: typer[all]>=0.9.0
Provides-Extra: ci
Requires-Dist: boto3==1.23.10; extra == 'ci'
Requires-Dist: coverage==6.2; extra == 'ci'
Requires-Dist: pglast==6.2; extra == 'ci'
Requires-Dist: pytest-cov==3.0.0; extra == 'ci'
Requires-Dist: pytest-mock==3.6.1; extra == 'ci'
Requires-Dist: pytest==7.0.1; extra == 'ci'
Requires-Dist: typer[all]==0.9.0; extra == 'ci'
Provides-Extra: dev
Requires-Dist: coverage>=6.2; extra == 'dev'
Requires-Dist: pytest-cov>=3.0.0; extra == 'dev'
Requires-Dist: pytest-mock>=3.6.1; extra == 'dev'
Requires-Dist: pytest>=7.0.1; extra == 'dev'
